docs_src/__init__.py
docs_src/conf.py
examples/__init__.py
examples/drive_file.py
examples/drive_folder.py
examples/drive_query.py
pygsuite/__init__.py
pygsuite/constants.py
pygsuite/enums.py
pygsuite/exceptions.py
pygsuite/py.typed
pygsuite/auth/__init__.py
pygsuite/auth/authorization.py
pygsuite/common/__init__.py
pygsuite/common/comment.py
pygsuite/common/link.py
pygsuite/common/parsing.py
pygsuite/common/style.py
pygsuite/docs/__init__.py
pygsuite/docs/body.py
pygsuite/docs/document.py
pygsuite/docs/element.py
pygsuite/docs/footers.py
pygsuite/docs/footnotes.py
pygsuite/docs/headers.py
pygsuite/docs/title.py
pygsuite/docs/doc_elements/__init__.py
pygsuite/docs/doc_elements/base_element.py
pygsuite/docs/doc_elements/footers.py
pygsuite/docs/doc_elements/footnotes.py
pygsuite/docs/doc_elements/headers.py
pygsuite/docs/doc_elements/paragraph.py
pygsuite/docs/doc_elements/section_break.py
pygsuite/docs/doc_elements/table.py
pygsuite/docs/doc_elements/table_of_contents.py
pygsuite/docs/doc_elements/paragraph_elements/__init__.py
pygsuite/docs/doc_elements/paragraph_elements/auto_text.py
pygsuite/docs/doc_elements/paragraph_elements/base_paragraph_element.py
pygsuite/docs/doc_elements/paragraph_elements/column_break.py
pygsuite/docs/doc_elements/paragraph_elements/equation.py
pygsuite/docs/doc_elements/paragraph_elements/footnote_reference.py
pygsuite/docs/doc_elements/paragraph_elements/horizontal_rule.py
pygsuite/docs/doc_elements/paragraph_elements/inline_object_element.py
pygsuite/docs/doc_elements/paragraph_elements/page_break.py
pygsuite/docs/doc_elements/paragraph_elements/text_run.py
pygsuite/drive/__init__.py
pygsuite/drive/drive.py
pygsuite/drive/drive_object.py
pygsuite/drive/file.py
pygsuite/drive/folder.py
pygsuite/drive/query.py
pygsuite/forms/__init__.py
pygsuite/forms/base_object.py
pygsuite/forms/enums.py
pygsuite/forms/form.py
pygsuite/forms/synchronizer.py
pygsuite/forms/generated/__init__.py
pygsuite/forms/generated/answer.py
pygsuite-0.0.19.dist-info/LICENSE
pygsuite-0.0.19.dist-info/METADATA
pygsuite-0.0.19.dist-info/WHEEL
pygsuite-0.0.19.dist-info/top_level.txt
pygsuite-0.0.19.dist-info/RECORD
