Metadata-Version: 2.1
Name: pygsuite
Version: 0.0.19
Summary: Package for working with the Gsuite set of tools.
Home-page: https://github.com/greenmtnboy/pygsuite
Author: greenmtnboy
Author-email: ethan.dickinson@gmail.com
License: UNKNOWN
Platform: UNKNOWN
Classifier: Development Status :: 2 - Pre-Alpha
Classifier: Programming Language :: Python
Classifier: Programming Language :: Python :: 3
Classifier: Programming Language :: Python :: 3.6
Classifier: Programming Language :: Python :: 3.7
Classifier: Programming Language :: Python :: 3.8
Classifier: Programming Language :: Python :: 3.9
Classifier: Programming Language :: Python :: 3.10
License-File: LICENSE
Requires-Dist: filetype
Requires-Dist: google-api-python-client
Requires-Dist: google-auth-httplib2
Requires-Dist: google-auth-oauthlib
Requires-Dist: jinja2 (>=2.11.0)
Requires-Dist: pandas (>=1.0.5)
Provides-Extra: images
Requires-Dist: google-cloud-storage ; extra == 'images'
Requires-Dist: pyopenssl ; extra == 'images'
